nester.py
PyPI_nester-1.3.1.dist-info/LICENSE.txt
PyPI_nester-1.3.1.dist-info/METADATA
PyPI_nester-1.3.1.dist-info/WHEEL
PyPI_nester-1.3.1.dist-info/top_level.txt
PyPI_nester-1.3.1.dist-info/RECORD
